zenc-0.1.0.dist-info/METADATA
zenc-0.1.0.dist-info/WHEEL
zenc/__init__.py
zenc/zenc.pyd
zenc-0.1.0.dist-info/RECORD
