Metadata-Version: 2.4
Name: zenc
Version: 0.1.0
Classifier: Programming Language :: Python
Classifier: Programming Language :: Rust
Classifier: Topic :: Security :: Cryptography
Classifier: License :: OSI Approved :: MIT License
Classifier: License :: OSI Approved :: Apache Software License
Summary: Streaming AEAD file encryption/decryption (Rust) with Python bindings
Author-email: Your Name <you@example.com>
License: MIT OR Apache-2.0
Requires-Python: >=3.8
